Metadata-Version: 1.0
Name: python-phone-number-jp
Version: 0.3.2
Summary: Parse Phone numbers of Japan.
Home-page: https://github.com/torico-tokyo/python-phone-number-jp.git
Author: ytyng
Author-email: ytyng@live.jp
License: BSD
Keywords: phone numbers japan.
Platform: UNKNOWN
